nlu/__init__.py
nlu/info.py
nlu/namespace.py
nlu/pipe_components.py
nlu/pipeline.py
zfiddling/__init__.py
zfiddling/argskwargsschmargs.py
zfiddling/fiddle.py
zfiddling/fiddle2.py
zfiddling/old_features.py
zfiddling/sample_pip/__init__.py
zfiddling/sample_pip/setup.py
peanutbuterdatatime-0.0.1.dist-info/LICENSE
peanutbuterdatatime-0.0.1.dist-info/METADATA
peanutbuterdatatime-0.0.1.dist-info/WHEEL
peanutbuterdatatime-0.0.1.dist-info/top_level.txt
peanutbuterdatatime-0.0.1.dist-info/RECORD
